{
    "data" : [
        {
            "number" : "1",
            "title" : "Lorem ipsum dolor sit amet consectetur adipisicing elit.",
            "Date" : "2021-12-24"
        },
        {
            "number" : "2",
            "title" : "Lorem ipsum dolor sit amet consectetur adipisicing elit.",
            "Date" : "2021-12-25"
        },
        {
            "number" : "3",
            "title" : "Lorem ipsum dolor sit amet consectetur adipisicing elit.",
            "Date" : "2021-12-26"
        },
        {
            "number" : "4",
            "title" : "Lorem ipsum dolor sit amet consectetur adipisicing elit.",
            "Date" : "2021-12-27"
        }

    ]
}